MANIFEST.in
README.md
setup.py
datapipeml/__init__.py
datapipeml/data_pipe.py
datapipeml/exceptions.py
datapipeml/one_hot_encoder.py
datapipeml/type_check.py
datapipeml.egg-info/PKG-INFO
datapipeml.egg-info/SOURCES.txt
datapipeml.egg-info/dependency_links.txt
datapipeml.egg-info/not-zip-safe
datapipeml.egg-info/requires.txt
datapipeml.egg-info/top_level.txt