Metadata-Version: 1.0
Name: datapipeml
Version: 0.8
Summary: Framework to manipulate dataframes fluidly in a pipeline.
Home-page: https://github.com/tiagohcalves/data-pipeline
Author: Tiago Alves
Author-email: tiagohcalves@gmail.com
License: MIT
Keywords: pandas pipeline machine learning dataset etl
Platform: UNKNOWN
